save_page_now_api/__init__.py
save_page_now_api/_version.py
save_page_now_api/exception.py
save_page_now_api/save_page_now_api.py
save_page_now_api/save_page_option.py
save_page_now_api-0.1.2.dist-info/licenses/LICENSE
save_page_now_api-0.1.2.dist-info/METADATA
save_page_now_api-0.1.2.dist-info/WHEEL
save_page_now_api-0.1.2.dist-info/top_level.txt
save_page_now_api-0.1.2.dist-info/RECORD
